Workbook

Sheet Cover
A1: PERSONAL RETIREMENT FINANCIAL PLAN
A2: [Your Name] & [Spouse Name] | Retirement Date: [Target Date]
A3: Prepared [Month Year] | For review with your financial planner & tax advisor
B5: RETIREMENT DATE
B6: Dec 31, 2027
B8: TOTAL NET WORTH (all sources)
B9: =SUM('Net Worth'!B4:B10) -> 1970000
B11: COMBINED RETIREMENT ACCOUNTS (401k/403b/IRA)
B12: =Assumptions!E27+Assumptions!E28 -> 30000.025
B14: CASH SAVINGS
B15: =Assumptions!E30 -> 0
B17: KEY MILESTONE DATES
B18: You — born | C18: [Month/Year] | D18: Age at retirement | E18: =Assumptions!B8 -> 60
B19: Spouse — born | C19: [Month/Year] | D19: Age at retirement | E19: =Assumptions!B9 -> 58
B20: Your 59½ (penalty-free 401k) | C20: [Date]
B21: Your Medicare eligibility | C21: [Date] | D21: Spouse Medicare | E21: [Date]
B22: Spouse Social Security @ 70 | C22: [Year] | D22: Your Social Security @ 70 | E22: [Year]
B23: Spouse RMDs begin | C23: [Year] | D23: Your RMDs begin | E23: [Year]
B25: WORKBOOK GUIDE
B26: 1. Cover | C26: This page — key facts and milestone dates
B27: 2. Assumptions | C27: All inputs — update annually (yellow cells)
B28: 3. Phase Plan | C28: Annual after-tax cash flow across retirement phases
B29: 4. Tax Calculator | C29: Federal + state bracket calculations by year
B30: 5. Roth Conversion | C30: Multi-year conversion tracker and strategy
B31: 6. Net Worth | C31: Wealth trajectory over time

Sheet Assumptions
A1: ASSUMPTIONS & INPUTS — Yellow = update annually | Edit every yellow cell for your own numbers
A3: PERSONAL | D3: INCOME & DEFERRALS | G3: FEDERAL TAX BRACKETS (MFJ, example year)
A4: Retirement date | B4: Dec 31, 2027 | D4: Deferred comp balance (if any) | E4: 0 | G4: 10% bracket top | H4: 23850
A5: Your birth month/year | B5: [MM/YYYY] | D5: Deferred comp distribution years | E5: 0 | G5: 12% bracket top | H5: 96950
A6: Spouse birth month/year | B6: [MM/YYYY] | D6: Plan return rate | E6: 0.06 | G6: 22% bracket top | H6: 206700
A7: Dependent(s) birth month/year | B7: [MM/YYYY] | D7: Est. Year 1 distribution (auto) | E7: =IFERROR(E4/E5*(1+E6),0) -> 0 | G7: 24% bracket top | H7: 394600
A8: Your age at retirement | B8: 60 | D8: EXPENSES | G8: 32% bracket top | H8: 501050
A9: Spouse age at retirement | B9: 58 | D9: Monthly living expenses (today's dollars) | E9: 8000 | G9: 35% bracket top | H9: 751600
A10: Your life expectancy (planning age) | B10: 90 | D10: Living expense inflation rate | E10: 0.03 | G10: 37% rate above top bracket | H10: 0.37
A11: Spouse life expectancy (planning age) | B11: 92 | D11: Healthcare — employer plan (while working, monthly) | E11: 500 | G11: Standard deduction (MFJ) | H11: 31500
A12: Your Social Security claim age | B12: 70 | D12: Healthcare — retiree/marketplace plan (monthly) | E12: 1800 | G12: SS federal taxable portion (max) | H12: 0.85
A13: Spouse Social Security claim age | B13: 70 | D13: Healthcare inflation rate | E13: 0.05
A14: Your 59½ date | B14: [Month/Year] | D14: Healthcare — one spouse only (post other's Medicare) | E14: 700 | G14: STATE TAX (example — CA MFJ)
A15: Your Medicare date | B15: [Month/Year] | D15: Healthcare — both on Medicare (monthly) | E15: 500 | G15: 1% bracket top | H15: 21512
A16: Spouse Medicare date | B16: [Month/Year] | G16: 2% bracket top | H16: 50998
A17: Spouse SS start year | B17: 2035 | D17: INVESTMENTS & RETIREMENT | G17: 4% bracket top | H17: 80490
A18: Your SS start year | B18: 2037 | D18: Your 401(k)/403(b) balance | E18: 1000000 | G18: 6% bracket top | H18: 111732
A19: Spouse RMD start year | B19: 2040 | D19: Spouse 401(k)/403(b) balance | E19: 800000 | G19: 8% bracket top | H19: 141212
A20: Your RMD start year | B20: 2042 | D20: HSA balance | E20: 20000 | G20: 9.3% bracket top | H20: 721318
A21: Dependent(s) off healthcare year | B21: 2030 | D21: Cash savings | E21: 150000 | G21: 10.3%+ above | H21: 0.103
D22: 401(k) growth rate | E22: 0.06 | G22: State taxes SS income? (0=no,1=yes) | H22: 0
A23: ANNUAL COMPENSATION (final working year) | D23: Savings return rate | E23: 0.04 | G23: NIIT rate (federal, high earners) | H23: 0.038
A24: Annual base salary | B24: 200000 | D24: HSA growth rate | E24: 0.06 | G24: LT capital gains rate (federal) | H24: 0.15
A25: Annual bonus (if any) | B25: 30000 | D25: Annual Roth conversion target | E25: 100000
A26: 401(k)/403(b) contribution (annual) | B26: 23000 | D26: Your SS benefit at 70 (annual) | E26: 42000
A27: HSA contribution (family max) | B27: 8550 | D27: Spouse SS benefit at 70 (annual) | E27: 30000
A28: Combined Fed + State marginal tax rate on W-2 | B28: 0.35 | D28: SS COLA rate | E28: 0.025
A30: RENTAL / OTHER INCOME (optional)
A31: Net rental income/mo (all properties, after mortgage+mgmt) | B31: 3000
A32: Rental income growth rate | B32: 0.03

Sheet Phase Plan
A1: ANNUAL AFTER-TAX CASH FLOW PLAN — Illustrative 10-Year Window (Inflation-Adjusted)
A2: YEAR | B2: 2027 | C2: 2028 | D2: 2029 | E2: 2030 | F2: 2031 | G2: 2032 | H2: 2033 | I2: 2034 | J2: 2035 | K2: 2036
A4: GROSS INCOME SOURCES
A5: Deferred Compensation (gross) | B5: =IF(0<Assumptions!$E$5,Assumptions!$E$7*(1+Assumptions!$E$6)^0,0) -> 0 | C5: =IF(1<Assumptions!$E$5,Assumptions!$E$7*(1+Assumptions!$E$6)^1,0) -> 0 | D5: =IF(2<Assumptions!$E$5,Assumptions!$E$7*(1+Assumptions!$E$6)^2,0) -> 0 | E5: =IF(3<Assumptions!$E$5,Assumptions!$E$7*(1+Assumptions!$E$6)^3,0) -> 0 | F5: =IF(4<Assumptions!$E$5,Assumptions!$E$7*(1+Assumptions!$E$6)^4,0) -> 0 | G5: =IF(5<Assumptions!$E$5,Assumptions!$E$7*(1+Assumptions!$E$6)^5,0) -> 0 | H5: =IF(6<Assumptions!$E$5,Assumptions!$E$7*(1+Assumptions!$E$6)^6,0) -> 0 | I5: =IF(7<Assumptions!$E$5,Assumptions!$E$7*(1+Assumptions!$E$6)^7,0) -> 0 | J5: =IF(8<Assumptions!$E$5,Assumptions!$E$7*(1+Assumptions!$E$6)^8,0) -> 0 | K5: =IF(9<Assumptions!$E$5,Assumptions!$E$7*(1+Assumptions!$E$6)^9,0) -> 0
A6: Rental / Other Income (net) | B6: =Assumptions!$B$31*12*(1+Assumptions!$B$32)^0 -> 36000 | C6: =Assumptions!$B$31*12*(1+Assumptions!$B$32)^1 -> 37080 | D6: =Assumptions!$B$31*12*(1+Assumptions!$B$32)^2 -> 38192.4 | E6: =Assumptions!$B$31*12*(1+Assumptions!$B$32)^3 -> 39338.172 | F6: =Assumptions!$B$31*12*(1+Assumptions!$B$32)^4 -> 40518.317 | G6: =Assumptions!$B$31*12*(1+Assumptions!$B$32)^5 -> 41733.867 | H6: =Assumptions!$B$31*12*(1+Assumptions!$B$32)^6 -> 42985.883 | I6: =Assumptions!$B$31*12*(1+Assumptions!$B$32)^7 -> 44275.459 | J6: =Assumptions!$B$31*12*(1+Assumptions!$B$32)^8 -> 45603.723 | K6: =Assumptions!$B$31*12*(1+Assumptions!$B$32)^9 -> 46971.835
A7: Spouse Social Security (COLA-adjusted) | B7: =IF(B$2>=Assumptions!$B$17,Assumptions!$E$27*(1+Assumptions!$E$28)^MAX(0,B$2-Assumptions!$B$17),0) -> 0 | C7: =IF(C$2>=Assumptions!$B$17,Assumptions!$E$27*(1+Assumptions!$E$28)^MAX(0,C$2-Assumptions!$B$17),0) -> 0 | D7: =IF(D$2>=Assumptions!$B$17,Assumptions!$E$27*(1+Assumptions!$E$28)^MAX(0,D$2-Assumptions!$B$17),0) -> 0 | E7: =IF(E$2>=Assumptions!$B$17,Assumptions!$E$27*(1+Assumptions!$E$28)^MAX(0,E$2-Assumptions!$B$17),0) -> 0 | F7: =IF(F$2>=Assumptions!$B$17,Assumptions!$E$27*(1+Assumptions!$E$28)^MAX(0,F$2-Assumptions!$B$17),0) -> 0 | G7: =IF(G$2>=Assumptions!$B$17,Assumptions!$E$27*(1+Assumptions!$E$28)^MAX(0,G$2-Assumptions!$B$17),0) -> 0 | H7: =IF(H$2>=Assumptions!$B$17,Assumptions!$E$27*(1+Assumptions!$E$28)^MAX(0,H$2-Assumptions!$B$17),0) -> 0 | I7: =IF(I$2>=Assumptions!$B$17,Assumptions!$E$27*(1+Assumptions!$E$28)^MAX(0,I$2-Assumptions!$B$17),0) -> 0 | ... K7: =IF(K$2>=Assumptions!$B$17,Assumptions!$E$27*(1+Assumptions!$E$28)^MAX(0,K$2-Assumptions!$B$17),0) -> 30750
A8: Your Social Security (COLA-adjusted) | B8: =IF(B$2>=Assumptions!$B$18,Assumptions!$E$26*(1+Assumptions!$E$28)^MAX(0,B$2-Assumptions!$B$18),0) -> 0 | C8: =IF(C$2>=Assumptions!$B$18,Assumptions!$E$26*(1+Assumptions!$E$28)^MAX(0,C$2-Assumptions!$B$18),0) -> 0 | D8: =IF(D$2>=Assumptions!$B$18,Assumptions!$E$26*(1+Assumptions!$E$28)^MAX(0,D$2-Assumptions!$B$18),0) -> 0 | E8: =IF(E$2>=Assumptions!$B$18,Assumptions!$E$26*(1+Assumptions!$E$28)^MAX(0,E$2-Assumptions!$B$18),0) -> 0 | F8: =IF(F$2>=Assumptions!$B$18,Assumptions!$E$26*(1+Assumptions!$E$28)^MAX(0,F$2-Assumptions!$B$18),0) -> 0 | G8: =IF(G$2>=Assumptions!$B$18,Assumptions!$E$26*(1+Assumptions!$E$28)^MAX(0,G$2-Assumptions!$B$18),0) -> 0 | H8: =IF(H$2>=Assumptions!$B$18,Assumptions!$E$26*(1+Assumptions!$E$28)^MAX(0,H$2-Assumptions!$B$18),0) -> 0 | I8: =IF(I$2>=Assumptions!$B$18,Assumptions!$E$26*(1+Assumptions!$E$28)^MAX(0,I$2-Assumptions!$B$18),0) -> 0 | ... K8: =IF(K$2>=Assumptions!$B$18,Assumptions!$E$26*(1+Assumptions!$E$28)^MAX(0,K$2-Assumptions!$B$18),0) -> 0
A9: TOTAL GROSS INCOME | B9: =SUM(B5:B8) -> 36000 | C9: =SUM(C5:C8) -> 37080 | D9: =SUM(D5:D8) -> 38192.4 | E9: =SUM(E5:E8) -> 39338.172 | F9: =SUM(F5:F8) -> 40518.317 | G9: =SUM(G5:G8) -> 41733.867 | H9: =SUM(H5:H8) -> 42985.883 | I9: =SUM(I5:I8) -> 44275.459 | ... K9: =SUM(K5:K8) -> 77721.835
A11: EXPENSES (inflation-adjusted)
A12: Living Expenses | B12: =-Assumptions!$E$9*12*(1+Assumptions!$E$10)^0 -> -96000 | C12: =-Assumptions!$E$9*12*(1+Assumptions!$E$10)^1 -> -98880 | D12: =-Assumptions!$E$9*12*(1+Assumptions!$E$10)^2 -> -101846.4 | E12: =-Assumptions!$E$9*12*(1+Assumptions!$E$10)^3 -> -104901.79 | F12: =-Assumptions!$E$9*12*(1+Assumptions!$E$10)^4 -> -108048.85 | G12: =-Assumptions!$E$9*12*(1+Assumptions!$E$10)^5 -> -111290.31 | H12: =-Assumptions!$E$9*12*(1+Assumptions!$E$10)^6 -> -114629.02 | I12: =-Assumptions!$E$9*12*(1+Assumptions!$E$10)^7 -> -118067.89 | J12: =-Assumptions!$E$9*12*(1+Assumptions!$E$10)^8 -> -121609.93 | K12: =-Assumptions!$E$9*12*(1+Assumptions!$E$10)^9 -> -125258.23
A13: Healthcare | B13: =-Assumptions!$E$12*12*(1+Assumptions!$E$13)^0 -> -21600 | C13: =-Assumptions!$E$12*12*(1+Assumptions!$E$13)^1 -> -22680 | D13: =-Assumptions!$E$12*12*(1+Assumptions!$E$13)^2 -> -23814 | E13: =-Assumptions!$E$12*12*(1+Assumptions!$E$13)^3 -> -25004.7 | F13: =-Assumptions!$E$12*12*(1+Assumptions!$E$13)^4 -> -26254.935 | G13: =-Assumptions!$E$12*12*(1+Assumptions!$E$13)^5 -> -27567.682 | H13: =-Assumptions!$E$12*12*(1+Assumptions!$E$13)^6 -> -28946.066 | I13: =-Assumptions!$E$12*12*(1+Assumptions!$E$13)^7 -> -30393.369 | J13: =-Assumptions!$E$12*12*(1+Assumptions!$E$13)^8 -> -31913.038 | K13: =-Assumptions!$E$12*12*(1+Assumptions!$E$13)^9 -> -33508.689
A14: TOTAL EXPENSES | B14: =SUM(B12:B13) -> -117600 | C14: =SUM(C12:C13) -> -121560 | D14: =SUM(D12:D13) -> -125660.4 | E14: =SUM(E12:E13) -> -129906.49 | F14: =SUM(F12:F13) -> -134303.78 | G14: =SUM(G12:G13) -> -138857.99 | H14: =SUM(H12:H13) -> -143575.09 | I14: =SUM(I12:I13) -> -148461.26 | ... K14: =SUM(K12:K13) -> -158766.92
A16: GAP & FUNDING
A17: Net Gap Before Withdrawal (income - expenses) | B17: =B9+B14 -> -81600 | C17: =C9+C14 -> -84480 | D17: =D9+D14 -> -87468 | E17: =E9+E14 -> -90568.32 | F17: =F9+F14 -> -93785.464 | G17: =G9+G14 -> -97124.126 | H17: =H9+H14 -> -100589.2 | I17: =I9+I14 -> -104185.8 | ... K17: =K9+K14 -> -81045.08
A18: Est. Tax on Withdrawals (approx. — see Tax Calculator for precision) | B18: =-MAX(0,-B17)*0.28 -> -22848 | C18: =-MAX(0,-C17)*0.28 -> -23654.4 | D18: =-MAX(0,-D17)*0.28 -> -24491.04 | E18: =-MAX(0,-E17)*0.28 -> -25359.13 | F18: =-MAX(0,-F17)*0.28 -> -26259.93 | G18: =-MAX(0,-G17)*0.28 -> -27194.755 | H18: =-MAX(0,-H17)*0.28 -> -28164.977 | I18: =-MAX(0,-I17)*0.28 -> -29172.024 | ... K18: =-MAX(0,-K17)*0.28 -> -22692.623
A19: 401(k) Gross Withdrawal Needed (grossed up) | B19: =MAX(0,-B17-B18) -> 104448 | C19: =MAX(0,-C17-C18) -> 108134.4 | D19: =MAX(0,-D17-D18) -> 111959.04 | E19: =MAX(0,-E17-E18) -> 115927.45 | F19: =MAX(0,-F17-F18) -> 120045.39 | G19: =MAX(0,-G17-G18) -> 124318.88 | H19: =MAX(0,-H17-H18) -> 128754.18 | I19: =MAX(0,-I17-I18) -> 133357.83 | ... K19: =MAX(0,-K17-K18) -> 103737.7
A21: PHASE (edit to match your own milestones) | B21: Ph1 — Bridge Year | C21: Ph1 | D21: Ph2 — Stabilizing | E21: Ph2 | F21: Ph3 — Mortgage-Free | G21: Ph3 | H21: Ph4 — Pre-SS | I21: Ph4 | J21: Ph5 — SS Begins | K21: Ph5

Sheet Tax Calculator
A1: FEDERAL & STATE TAX CALCULATOR — MFJ (simplified, tiered brackets)
A2: Year | B2: 2027 | C2: 2028 | D2: 2029 | E2: 2030 | F2: 2031 | G2: 2032 | H2: 2033 | I2: 2034 | J2: 2035 | K2: 2036
A4: TOTAL GROSS INCOME (from Phase Plan) | B4: ='Phase Plan'!B9+'Phase Plan'!B19 -> 140448 | C4: ='Phase Plan'!C9+'Phase Plan'!C19 -> 145214.4 | D4: ='Phase Plan'!D9+'Phase Plan'!D19 -> 150151.44 | E4: ='Phase Plan'!E9+'Phase Plan'!E19 -> 155265.62 | F4: ='Phase Plan'!F9+'Phase Plan'!F19 -> 160563.71 | G4: ='Phase Plan'!G9+'Phase Plan'!G19 -> 166052.75 | H4: ='Phase Plan'!H9+'Phase Plan'!H19 -> 171740.06 | I4: ='Phase Plan'!I9+'Phase Plan'!I19 -> 177633.28 | ... K4: ='Phase Plan'!K9+'Phase Plan'!K19 -> 181459.54
A5: Standard Deduction | B5: =-Assumptions!$H$11 -> -31500 | C5: =-Assumptions!$H$11 -> -31500 | D5: =-Assumptions!$H$11 -> -31500 | E5: =-Assumptions!$H$11 -> -31500 | F5: =-Assumptions!$H$11 -> -31500 | G5: =-Assumptions!$H$11 -> -31500 | H5: =-Assumptions!$H$11 -> -31500 | I5: =-Assumptions!$H$11 -> -31500 | ... K5: =-Assumptions!$H$11 -> -31500
A6: TAXABLE INCOME | B6: =MAX(0,B4+B5) -> 108948 | C6: =MAX(0,C4+C5) -> 113714.4 | D6: =MAX(0,D4+D5) -> 118651.44 | E6: =MAX(0,E4+E5) -> 123765.62 | F6: =MAX(0,F4+F5) -> 129063.71 | G6: =MAX(0,G4+G5) -> 134552.75 | H6: =MAX(0,H4+H5) -> 140240.06 | I6: =MAX(0,I4+I5) -> 146133.28 | ... K6: =MAX(0,K4+K5) -> 149959.54
A8: Federal Income Tax (tiered brackets, simplified) | B8: =10%*MIN(B6,Assumptions!$H$4)+12%*MAX(0,MIN(B6,Assumptions!$H$5)-Assumptions!$H$4)+22%*MAX(0,MIN(B6,Assumptions!$H$6)-Assumptions!$H$5)+24%*MAX(0,MIN(B6,Assumptions!$H$7)-Assumptions!$H$6)+32%*MAX(0,MIN(B6,Assumptions!$H$8)-Assumptions!$H$7)+35%*MAX(0,MIN(B6,Assumptions!$H$9)-Assumptions!$H$8)+Assumptions!$H$10*MAX(0,B6-Assumptions!$H$9) -> 13796.56 | C8: =10%*MIN(C6,Assumptions!$H$4)+12%*MAX(0,MIN(C6,Assumptions!$H$5)-Assumptions!$H$4)+22%*MAX(0,MIN(C6,Assumptions!$H$6)-Assumptions!$H$5)+24%*MAX(0,MIN(C6,Assumptions!$H$7)-Assumptions!$H$6)+32%*MAX(0,MIN(C6,Assumptions!$H$8)-Assumptions!$H$7)+35%*MAX(0,MIN(C6,Assumptions!$H$9)-Assumptions!$H$8)+Assumptions!$H$10*MAX(0,C6-Assumptions!$H$9) -> 14845.168 | D8: =10%*MIN(D6,Assumptions!$H$4)+12%*MAX(0,MIN(D6,Assumptions!$H$5)-Assumptions!$H$4)+22%*MAX(0,MIN(D6,Assumptions!$H$6)-Assumptions!$H$5)+24%*MAX(0,MIN(D6,Assumptions!$H$7)-Assumptions!$H$6)+32%*MAX(0,MIN(D6,Assumptions!$H$8)-Assumptions!$H$7)+35%*MAX(0,MIN(D6,Assumptions!$H$9)-Assumptions!$H$8)+Assumptions!$H$10*MAX(0,D6-Assumptions!$H$9) -> 15931.317 | E8: =10%*MIN(E6,Assumptions!$H$4)+12%*MAX(0,MIN(E6,Assumptions!$H$5)-Assumptions!$H$4)+22%*MAX(0,MIN(E6,Assumptions!$H$6)-Assumptions!$H$5)+24%*MAX(0,MIN(E6,Assumptions!$H$7)-Assumptions!$H$6)+32%*MAX(0,MIN(E6,Assumptions!$H$8)-Assumptions!$H$7)+35%*MAX(0,MIN(E6,Assumptions!$H$9)-Assumptions!$H$8)+Assumptions!$H$10*MAX(0,E6-Assumptions!$H$9) -> 17056.437 | F8: =10%*MIN(F6,Assumptions!$H$4)+12%*MAX(0,MIN(F6,Assumptions!$H$5)-Assumptions!$H$4)+22%*MAX(0,MIN(F6,Assumptions!$H$6)-Assumptions!$H$5)+24%*MAX(0,MIN(F6,Assumptions!$H$7)-Assumptions!$H$6)+32%*MAX(0,MIN(F6,Assumptions!$H$8)-Assumptions!$H$7)+35%*MAX(0,MIN(F6,Assumptions!$H$9)-Assumptions!$H$8)+Assumptions!$H$10*MAX(0,F6-Assumptions!$H$9) -> 18222.016 | G8: =10%*MIN(G6,Assumptions!$H$4)+12%*MAX(0,MIN(G6,Assumptions!$H$5)-Assumptions!$H$4)+22%*MAX(0,MIN(G6,Assumptions!$H$6)-Assumptions!$H$5)+24%*MAX(0,MIN(G6,Assumptions!$H$7)-Assumptions!$H$6)+32%*MAX(0,MIN(G6,Assumptions!$H$8)-Assumptions!$H$7)+35%*MAX(0,MIN(G6,Assumptions!$H$9)-Assumptions!$H$8)+Assumptions!$H$10*MAX(0,G6-Assumptions!$H$9) -> 19429.605 | H8: =10%*MIN(H6,Assumptions!$H$4)+12%*MAX(0,MIN(H6,Assumptions!$H$5)-Assumptions!$H$4)+22%*MAX(0,MIN(H6,Assumptions!$H$6)-Assumptions!$H$5)+24%*MAX(0,MIN(H6,Assumptions!$H$7)-Assumptions!$H$6)+32%*MAX(0,MIN(H6,Assumptions!$H$8)-Assumptions!$H$7)+35%*MAX(0,MIN(H6,Assumptions!$H$9)-Assumptions!$H$8)+Assumptions!$H$10*MAX(0,H6-Assumptions!$H$9) -> 20680.814 | I8: =10%*MIN(I6,Assumptions!$H$4)+12%*MAX(0,MIN(I6,Assumptions!$H$5)-Assumptions!$H$4)+22%*MAX(0,MIN(I6,Assumptions!$H$6)-Assumptions!$H$5)+24%*MAX(0,MIN(I6,Assumptions!$H$7)-Assumptions!$H$6)+32%*MAX(0,MIN(I6,Assumptions!$H$8)-Assumptions!$H$7)+35%*MAX(0,MIN(I6,Assumptions!$H$9)-Assumptions!$H$8)+Assumptions!$H$10*MAX(0,I6-Assumptions!$H$9) -> 21977.323 | ... K8: =10%*MIN(K6,Assumptions!$H$4)+12%*MAX(0,MIN(K6,Assumptions!$H$5)-Assumptions!$H$4)+22%*MAX(0,MIN(K6,Assumptions!$H$6)-Assumptions!$H$5)+24%*MAX(0,MIN(K6,Assumptions!$H$7)-Assumptions!$H$6)+32%*MAX(0,MIN(K6,Assumptions!$H$8)-Assumptions!$H$7)+35%*MAX(0,MIN(K6,Assumptions!$H$9)-Assumptions!$H$8)+Assumptions!$H$10*MAX(0,K6-Assumptions!$H$9) -> 22819.098
A9: Federal Effective Rate | B9: =IFERROR(B8/B6,0) -> 0.12663436 | C9: =IFERROR(C8/C6,0) -> 0.13054783 | D9: =IFERROR(D8/D6,0) -> 0.1342699 | E9: =IFERROR(E8/E6,0) -> 0.1378124 | F9: =IFERROR(F8/F6,0) -> 0.14118621 | G9: =IFERROR(G8/G6,0) -> 0.1444014 | H9: =IFERROR(H8/H6,0) -> 0.14746723 | I9: =IFERROR(I8/I6,0) -> 0.15039231 | ... K9: =IFERROR(K8/K6,0) -> 0.15216837
A11: State Income Tax (simplified, top-bracket blended) | B11: =MIN(B6,Assumptions!$H$18)*4%+MAX(0,B6-Assumptions!$H$18)*9.3% -> 4357.92 | C11: =MIN(C6,Assumptions!$H$18)*4%+MAX(0,C6-Assumptions!$H$18)*9.3% -> 4653.6432 | D11: =MIN(D6,Assumptions!$H$18)*4%+MAX(0,D6-Assumptions!$H$18)*9.3% -> 5112.7879 | E11: =MIN(E6,Assumptions!$H$18)*4%+MAX(0,E6-Assumptions!$H$18)*9.3% -> 5588.4068 | F11: =MIN(F6,Assumptions!$H$18)*4%+MAX(0,F6-Assumptions!$H$18)*9.3% -> 6081.1291 | G11: =MIN(G6,Assumptions!$H$18)*4%+MAX(0,G6-Assumptions!$H$18)*9.3% -> 6591.6096 | H11: =MIN(H6,Assumptions!$H$18)*4%+MAX(0,H6-Assumptions!$H$18)*9.3% -> 7120.5299 | I11: =MIN(I6,Assumptions!$H$18)*4%+MAX(0,I6-Assumptions!$H$18)*9.3% -> 7668.5995 | ... K11: =MIN(K6,Assumptions!$H$18)*4%+MAX(0,K6-Assumptions!$H$18)*9.3% -> 8024.441
A13: NIIT (3.8% on rental + investment income, approx.) | B13: ='Phase Plan'!B6*Assumptions!$H$23 -> 1368 | C13: ='Phase Plan'!C6*Assumptions!$H$23 -> 1409.04 | D13: ='Phase Plan'!D6*Assumptions!$H$23 -> 1451.3112 | E13: ='Phase Plan'!E6*Assumptions!$H$23 -> 1494.8505 | F13: ='Phase Plan'!F6*Assumptions!$H$23 -> 1539.6961 | G13: ='Phase Plan'!G6*Assumptions!$H$23 -> 1585.8869 | H13: ='Phase Plan'!H6*Assumptions!$H$23 -> 1633.4635 | I13: ='Phase Plan'!I6*Assumptions!$H$23 -> 1682.4674 | ... K13: ='Phase Plan'!K6*Assumptions!$H$23 -> 1784.9297
A15: TOTAL TAX | B15: =B8+B11+B13 -> 19522.48 | C15: =C8+C11+C13 -> 20907.851 | D15: =D8+D11+D13 -> 22495.416 | E15: =E8+E11+E13 -> 24139.694 | F15: =F8+F11+F13 -> 25842.841 | G15: =G8+G11+G13 -> 27607.101 | H15: =H8+H11+H13 -> 29434.807 | I15: =I8+I11+I13 -> 31328.389 | ... K15: =K8+K11+K13 -> 32628.469
A16: Total Effective Rate | B16: =IFERROR(B15/B4,0) -> 0.13900148 | C16: =IFERROR(C15/C4,0) -> 0.14397919 | D16: =IFERROR(D15/D4,0) -> 0.14981818 | E16: =IFERROR(E15/E4,0) -> 0.15547353 | F16: =IFERROR(F15/F4,0) -> 0.1609507 | G16: =IFERROR(G15/G4,0) -> 0.16625501 | H16: =IFERROR(H15/H4,0) -> 0.17139162 | I16: =IFERROR(I15/I4,0) -> 0.17636554 | ... K16: =IFERROR(K15/K4,0) -> 0.17981126
A18: AFTER-TAX INCOME | B18: =B4-B15 -> 120925.52 | C18: =C4-C15 -> 124306.55 | D18: =D4-D15 -> 127656.02 | E18: =E4-E15 -> 131125.93 | F18: =F4-F15 -> 134720.87 | G18: =G4-G15 -> 138445.65 | H18: =H4-H15 -> 142305.26 | I18: =I4-I15 -> 146304.9 | ... K18: =K4-K15 -> 148831.07

Sheet Roth Conversion
A1: ROTH CONVERSION TRACKER — Multi-Year Strategy
A2: Year | B2: Traditional 401(k) (start of year) | C2: Roth Balance (cumulative) | D2: Annual Conversion | E2: Est. Tax on Conversion (~30%) | F2: 401(k) Withdrawal (for living expenses) | G2: Year-End 401(k) | H2: Strategy Notes
A3: 2027 | B3: =Assumptions!$E$18+Assumptions!$E$19 -> 1800000 | C3: 0 | D3: =Assumptions!$E$25 -> 100000 | E3: =D3*0.3 -> 30000 | F3: ='Phase Plan'!B19 -> 104448 | G3: =B3-D3-F3 -> 1595552 | H3: Prioritize the spouse with the larger balance first; convert into the top of your target bracket each year.
A4: 2028 | B4: =G3 -> 1595552 | C4: =C3+D3 -> 100000 | D4: =Assumptions!$E$25 -> 100000 | E4: =D4*0.3 -> 30000 | F4: ='Phase Plan'!C19 -> 108134.4 | G4: =B4-D4-F4 -> 1387417.6 | H4: Prioritize the spouse with the larger balance first; convert into the top of your target bracket each year.
A5: 2029 | B5: =G4 -> 1387417.6 | C5: =C4+D4 -> 200000 | D5: =Assumptions!$E$25 -> 100000 | E5: =D5*0.3 -> 30000 | F5: ='Phase Plan'!D19 -> 111959.04 | G5: =B5-D5-F5 -> 1175458.6 | H5: Prioritize the spouse with the larger balance first; convert into the top of your target bracket each year.
A6: 2030 | B6: =G5 -> 1175458.6 | C6: =C5+D5 -> 300000 | D6: =Assumptions!$E$25 -> 100000 | E6: =D6*0.3 -> 30000 | F6: ='Phase Plan'!E19 -> 115927.45 | G6: =B6-D6-F6 -> 959531.11 | H6: Prioritize the spouse with the larger balance first; convert into the top of your target bracket each year.
A7: 2031 | B7: =G6 -> 959531.11 | C7: =C6+D6 -> 400000 | D7: =Assumptions!$E$25 -> 100000 | E7: =D7*0.3 -> 30000 | F7: ='Phase Plan'!F19 -> 120045.39 | G7: =B7-D7-F7 -> 739485.72 | H7: Prioritize the spouse with the larger balance first; convert into the top of your target bracket each year.
A8: 2032 | B8: =G7 -> 739485.72 | C8: =C7+D7 -> 500000 | D8: =Assumptions!$E$25 -> 100000 | E8: =D8*0.3 -> 30000 | F8: ='Phase Plan'!G19 -> 124318.88 | G8: =B8-D8-F8 -> 515166.84 | H8: Prioritize the spouse with the larger balance first; convert into the top of your target bracket each year.
A9: 2033 | B9: =G8 -> 515166.84 | C9: =C8+D8 -> 600000 | D9: =Assumptions!$E$25 -> 100000 | E9: =D9*0.3 -> 30000 | F9: ='Phase Plan'!H19 -> 128754.18 | G9: =B9-D9-F9 -> 286412.65 | H9: Prioritize the spouse with the larger balance first; convert into the top of your target bracket each year.
A10: 2034 | B10: =G9 -> 286412.65 | C10: =C9+D9 -> 700000 | D10: =Assumptions!$E$25 -> 100000 | E10: =D10*0.3 -> 30000 | F10: ='Phase Plan'!I19 -> 133357.83 | G10: =B10-D10-F10 -> 53054.829 | H10: Prioritize the spouse with the larger balance first; convert into the top of your target bracket each year.
A11: 2035 | B11: =G10 -> 53054.829 | C11: =C10+D10 -> 800000 | D11: =Assumptions!$E$25 -> 100000 | E11: =D11*0.3 -> 30000 | F11: ='Phase Plan'!J19 -> 99736.63 | G11: =B11-D11-F11 -> -146681.8 | H11: Prioritize the spouse with the larger balance first; convert into the top of your target bracket each year.
A12: 2036 | B12: =G11 -> -146681.8 | C12: =C11+D11 -> 900000 | D12: =Assumptions!$E$25 -> 100000 | E12: =D12*0.3 -> 30000 | F12: ='Phase Plan'!K19 -> 103737.7 | G12: =B12-D12-F12 -> -350419.5 | H12: Prioritize the spouse with the larger balance first; convert into the top of your target bracket each year.
A14: KEY: The best conversion years are usually the ones with the least other taxable income (e.g. the first year or two after salary ends, before Social Security and RMDs begin). Re-run this tab whenever tax brackets or your balances change.

Sheet Net Worth
A1: NET WORTH PROJECTION (Nominal, illustrative)
A2: Asset Class | B2: 2027 | C2: 2028 | D2: 2029 | E2: 2030 | F2: 2031 | G2: 2032 | H2: 2033 | I2: 2034 | J2: 2035 | K2: 2036
A4: Your 401(k)/403(b) — Traditional (net of conversions/withdrawals, approx.) | B4: =MAX(0,'Roth Conversion'!B3*(Assumptions!$E$18/(Assumptions!$E$18+Assumptions!$E$19))) -> 1000000 | C4: =MAX(0,'Roth Conversion'!B4*(Assumptions!$E$18/(Assumptions!$E$18+Assumptions!$E$19))) -> 886417.78 | D4: =MAX(0,'Roth Conversion'!B5*(Assumptions!$E$18/(Assumptions!$E$18+Assumptions!$E$19))) -> 770787.56 | E4: =MAX(0,'Roth Conversion'!B6*(Assumptions!$E$18/(Assumptions!$E$18+Assumptions!$E$19))) -> 653032.53 | F4: =MAX(0,'Roth Conversion'!B7*(Assumptions!$E$18/(Assumptions!$E$18+Assumptions!$E$19))) -> 533072.84 | G4: =MAX(0,'Roth Conversion'!B8*(Assumptions!$E$18/(Assumptions!$E$18+Assumptions!$E$19))) -> 410825.4 | H4: =MAX(0,'Roth Conversion'!B9*(Assumptions!$E$18/(Assumptions!$E$18+Assumptions!$E$19))) -> 286203.8 | I4: =MAX(0,'Roth Conversion'!B10*(Assumptions!$E$18/(Assumptions!$E$18+Assumptions!$E$19))) -> 159118.14 | J4: =MAX(0,'Roth Conversion'!B11*(Assumptions!$E$18/(Assumptions!$E$18+Assumptions!$E$19))) -> 29474.905 | K4: =MAX(0,'Roth Conversion'!B12*(Assumptions!$E$18/(Assumptions!$E$18+Assumptions!$E$19))) -> 0
A5: Spouse 401(k)/403(b) — Traditional (approx.) | B5: =MAX(0,'Roth Conversion'!B3*(Assumptions!$E$19/(Assumptions!$E$18+Assumptions!$E$19))) -> 800000 | C5: =MAX(0,'Roth Conversion'!B4*(Assumptions!$E$19/(Assumptions!$E$18+Assumptions!$E$19))) -> 709134.22 | D5: =MAX(0,'Roth Conversion'!B5*(Assumptions!$E$19/(Assumptions!$E$18+Assumptions!$E$19))) -> 616630.04 | E5: =MAX(0,'Roth Conversion'!B6*(Assumptions!$E$19/(Assumptions!$E$18+Assumptions!$E$19))) -> 522426.03 | F5: =MAX(0,'Roth Conversion'!B7*(Assumptions!$E$19/(Assumptions!$E$18+Assumptions!$E$19))) -> 426458.27 | G5: =MAX(0,'Roth Conversion'!B8*(Assumptions!$E$19/(Assumptions!$E$18+Assumptions!$E$19))) -> 328660.32 | H5: =MAX(0,'Roth Conversion'!B9*(Assumptions!$E$19/(Assumptions!$E$18+Assumptions!$E$19))) -> 228963.04 | I5: =MAX(0,'Roth Conversion'!B10*(Assumptions!$E$19/(Assumptions!$E$18+Assumptions!$E$19))) -> 127294.51 | J5: =MAX(0,'Roth Conversion'!B11*(Assumptions!$E$19/(Assumptions!$E$18+Assumptions!$E$19))) -> 23579.924 | K5: =MAX(0,'Roth Conversion'!B12*(Assumptions!$E$19/(Assumptions!$E$18+Assumptions!$E$19))) -> 0
A6: Roth Accounts (converted) | B6: ='Roth Conversion'!C3 -> 0 | C6: ='Roth Conversion'!C4 -> 100000 | D6: ='Roth Conversion'!C5 -> 200000 | E6: ='Roth Conversion'!C6 -> 300000 | F6: ='Roth Conversion'!C7 -> 400000 | G6: ='Roth Conversion'!C8 -> 500000 | H6: ='Roth Conversion'!C9 -> 600000 | I6: ='Roth Conversion'!C10 -> 700000 | J6: ='Roth Conversion'!C11 -> 800000 | K6: ='Roth Conversion'!C12 -> 900000
A7: HSA Account | B7: =Assumptions!$E$20*(1+Assumptions!$E$24)^0 -> 20000 | C7: =Assumptions!$E$20*(1+Assumptions!$E$24)^1 -> 21200 | D7: =Assumptions!$E$20*(1+Assumptions!$E$24)^2 -> 22472 | E7: =Assumptions!$E$20*(1+Assumptions!$E$24)^3 -> 23820.32 | F7: =Assumptions!$E$20*(1+Assumptions!$E$24)^4 -> 25249.539 | G7: =Assumptions!$E$20*(1+Assumptions!$E$24)^5 -> 26764.512 | H7: =Assumptions!$E$20*(1+Assumptions!$E$24)^6 -> 28370.382 | I7: =Assumptions!$E$20*(1+Assumptions!$E$24)^7 -> 30072.605 | J7: =Assumptions!$E$20*(1+Assumptions!$E$24)^8 -> 31876.961 | K7: =Assumptions!$E$20*(1+Assumptions!$E$24)^9 -> 33789.579
A8: Cash Savings | B8: =Assumptions!$E$21*(1+Assumptions!$E$23)^0 -> 150000 | C8: =Assumptions!$E$21*(1+Assumptions!$E$23)^1 -> 156000 | D8: =Assumptions!$E$21*(1+Assumptions!$E$23)^2 -> 162240 | E8: =Assumptions!$E$21*(1+Assumptions!$E$23)^3 -> 168729.6 | F8: =Assumptions!$E$21*(1+Assumptions!$E$23)^4 -> 175478.78 | G8: =Assumptions!$E$21*(1+Assumptions!$E$23)^5 -> 182497.94 | H8: =Assumptions!$E$21*(1+Assumptions!$E$23)^6 -> 189797.85 | I8: =Assumptions!$E$21*(1+Assumptions!$E$23)^7 -> 197389.77 | J8: =Assumptions!$E$21*(1+Assumptions!$E$23)^8 -> 205285.36 | K8: =Assumptions!$E$21*(1+Assumptions!$E$23)^9 -> 213496.77
A9: Real Estate Equity (enter manually or link to a Properties tab) | B9: 0 | C9: 0 | D9: 0 | E9: 0 | F9: 0 | G9: 0 | H9: 0 | I9: 0 | J9: 0 | K9: 0
A11: TOTAL NET WORTH | B11: =SUM(B4:B9) -> 1970000 | C11: =SUM(C4:C9) -> 1872752 | D11: =SUM(D4:D9) -> 1772129.6 | E11: =SUM(E4:E9) -> 1668008.5 | F11: =SUM(F4:F9) -> 1560259.4 | G11: =SUM(G4:G9) -> 1448748.2 | H11: =SUM(H4:H9) -> 1333335.1 | I11: =SUM(I4:I9) -> 1213875 | ... K11: =SUM(K4:K9) -> 1147286.4
